<?xml version="1.0" encoding="UTF-8" ?>
<odoo>
    <record model="ir.ui.view" id="lims_quality_form">
        <field name="name">Lims quality view form</field>
        <field name="inherit_id" ref="quality.quality_point_view_form"/>
        <field name="model">quality.point</field>
        <field name="arch" type="xml">
            <xpath expr="//notebook" position="inside">
                <page string="Lims" name="lims">
                    <group>
                        <field name="create_analysis"/>
                        <field name="analysis_category_id"/>
                    </group>
                </page>
            </xpath>
        </field>
    </record>

    <record model="ir.ui.view" id="lims_quality_alert_view_form">
        <field name="name">Lims quality check view form</field>
        <field name="inherit_id" ref="quality_control.quality_check_view_form"/>
        <field name="model">quality.check</field>
        <field name="arch" type="xml">
            <xpath expr="//header" position="inside">
                <field name="rel_point_id_create_analysis" invisible="1"/>
                <button name="create_analysis" string="Create Analysis" class="oe_highlight" type="object"
                        attrs="{'invisible': [('rel_point_id_create_analysis', '=', False)]}"/>
                <button name="create_analysis_from_stock_move" string="Create Analysis from stock" class="oe_highlight"
                        type="object" attrs="{'invisible': [('picking_id', '=', False)]}"
                />
            </xpath>
            <xpath expr="//div[hasclass('oe_button_box')]" position="inside">
                <button name="open_analysis" type="object" icon="fa-flask" class="oe_stat_button">
                    <field string="Analysis" name="nb_analysis" widget="statinfo"/>
                </button>
            </xpath>
            <xpath expr="//field[@name='picking_id']" position="attributes">
                <attribute name="invisible">0</attribute>
            </xpath>
        </field>
    </record>

</odoo>
